LICENSE
MANIFEST.in
README.md
setup.py
irrtree/__init__.py
irrtree/cli.py
irrtree.egg-info/PKG-INFO
irrtree.egg-info/SOURCES.txt
irrtree.egg-info/dependency_links.txt
irrtree.egg-info/entry_points.txt
irrtree.egg-info/requires.txt
irrtree.egg-info/top_level.txt