Metadata-Version: 2.1
Name: irrtree
Version: 1.3.0
Summary: IRRTree
Home-page: https://github.com/job/irrtree
Maintainer: Job Snijders
Maintainer-email: job@instituut.net
License: BSD 2-Clause
Keywords: irr python bgp routing networking
Platform: UNKNOWN
Classifier: Intended Audience :: Developers
Classifier: Topic :: Software Development :: Libraries :: Python Modules
Classifier: Topic :: System :: Networking
Classifier: License :: OSI Approved :: BSD License
Classifier: Programming Language :: Python :: 2.7
